[
  {
    "fullName": "Rema Revelle",
    "boughtCar": 8,
    "spentMoney": 40586.91
  },
  {
    "fullName": "Yvonne Mccalla",
    "boughtCar": 5,
    "spentMoney": 27727.85
  },
  {
    "fullName": "Francis Mckim",
    "boughtCar": 5,
    "spentMoney": 23972.33
  },
  {
    "fullName": "Louann Holzworth",
    "boughtCar": 6,
    "spentMoney": 22880.36
  },
  {
    "fullName": "Faustina Burgher",
    "boughtCar": 5,
    "spentMoney": 22323.36
  },
  {
    "fullName": "Lino Subia",
    "boughtCar": 4,
    "spentMoney": 21820.50
  },
  {
    "fullName": "Jimmy Grossi",
    "boughtCar": 3,
    "spentMoney": 21033.48
  },
  {
    "fullName": "Garret Capron",
    "boughtCar": 4,
    "spentMoney": 18846.17
  },
  {
    "fullName": "Nisha Markwell",
    "boughtCar": 3,
    "spentMoney": 17942.79
  },
  {
    "fullName": "Carole Witman",
    "boughtCar": 5,
    "spentMoney": 17354.67
  },
  {
    "fullName": "Carri Knapik",
    "boughtCar": 2,
    "spentMoney": 15386.75
  },
  {
    "fullName": "Audrea Cardinal",
    "boughtCar": 2,
    "spentMoney": 13718.27
  },
  {
    "fullName": "Rico Peer",
    "boughtCar": 4,
    "spentMoney": 13555.58
  },
  {
    "fullName": "Marcelle Griego",
    "boughtCar": 3,
    "spentMoney": 13421.21
  },
  {
    "fullName": "Teddy Hobby",
    "boughtCar": 3,
    "spentMoney": 11429.53
  },
  {
    "fullName": "Taina Achenbach",
    "boughtCar": 4,
    "spentMoney": 11159.19
  },
  {
    "fullName": "Brett Brickley",
    "boughtCar": 3,
    "spentMoney": 10717.10
  },
  {
    "fullName": "Hai Everton",
    "boughtCar": 4,
    "spentMoney": 10525.44
  },
  {
    "fullName": "Cinthia Lasala",
    "boughtCar": 3,
    "spentMoney": 10406.61
  },
  {
    "fullName": "Donnetta Soliz",
    "boughtCar": 2,
    "spentMoney": 9635.44
  },
  {
    "fullName": "Emmitt Benally",
    "boughtCar": 3,
    "spentMoney": 9232.64
  },
  {
    "fullName": "Johnette Derryberry",
    "boughtCar": 4,
    "spentMoney": 8986.98
  },
  {
    "fullName": "Hipolito Lamoreaux",
    "boughtCar": 2,
    "spentMoney": 8913.01
  },
  {
    "fullName": "Kristian Engberg",
    "boughtCar": 2,
    "spentMoney": 8367.52
  },
  {
    "fullName": "Sylvie Mcelravy",
    "boughtCar": 4,
    "spentMoney": 8252.73
  },
  {
    "fullName": "Oren Perlman",
    "boughtCar": 2,
    "spentMoney": 7923.31
  },
  {
    "fullName": "Zada Attwood",
    "boughtCar": 2,
    "spentMoney": 5428.71
  },
  {
    "fullName": "Natalie Poli",
    "boughtCar": 2,
    "spentMoney": 4871.32
  },
  {
    "fullName": "Daniele Zarate",
    "boughtCar": 1,
    "spentMoney": 3666.94
  }
]